pandas_datareaders_unofficial/__init__.py
pandas_datareaders_unofficial/module.py
pandas_datareaders_unofficial/tools.py
pandas_datareaders_unofficial/datareaders/__init__.py
pandas_datareaders_unofficial/datareaders/base.py
pandas_datareaders_unofficial/datareaders/fama_french.py
pandas_datareaders_unofficial/datareaders/fred.py
pandas_datareaders_unofficial/datareaders/google_finance_daily.py
pandas_datareaders_unofficial/datareaders/google_finance_intraday.py
pandas_datareaders_unofficial/datareaders/google_finance_options.py
pandas_datareaders_unofficial/datareaders/openexchangerates.py
pandas_datareaders_unofficial/datareaders/world_bank.py
pandas_datareaders_unofficial/datareaders/yahoo_finance_daily.py
pandas_datareaders_unofficial/datareaders/yahoo_finance_intraday.py
pandas_datareaders_unofficial/datareaders/yahoo_finance_options.py
pandas_datareaders_unofficial/datareaders/yahoo_finance_quotes.py
pandas_datareaders_unofficial/datareaders/base/__init__.py
pandas_datareaders_unofficial/tools/__init__.py
pandas_datareaders_unofficial-0.0.4.dist-info/DESCRIPTION.rst
pandas_datareaders_unofficial-0.0.4.dist-info/entry_points.txt
pandas_datareaders_unofficial-0.0.4.dist-info/METADATA
pandas_datareaders_unofficial-0.0.4.dist-info/metadata.json
pandas_datareaders_unofficial-0.0.4.dist-info/RECORD
pandas_datareaders_unofficial-0.0.4.dist-info/top_level.txt
pandas_datareaders_unofficial-0.0.4.dist-info/WHEEL
