Metadata-Version: 1.1
Name: pandas-datareaders-unofficial
Version: 0.0.4
Summary: Pandas DataReaders with requests and requests-cache
Home-page: https://github.com/femtotrader/pandas_datareaders_unofficial
Author: Femto Trader
Author-email: femto.trader@gmail.com
License: BSD
Keywords: data io requests http https web
Platform: UNKNOWN
Classifier: Development Status :: 3 - Alpha
Classifier: Environment :: Console
Classifier: Intended Audience :: Science/Research
Classifier: Operating System :: OS Independent
Classifier: Topic :: Scientific/Engineering
Classifier: License :: OSI Approved :: BSD License
Classifier: Programming Language :: Cython
Classifier: Programming Language :: Python
Classifier: Programming Language :: Python :: 2.7
Classifier: Programming Language :: Python :: 3.3
Classifier: Programming Language :: Python :: 3.4
